log_manager_cli/__init__.py
log_manager_cli/config.py
log_manager_cli/crypto_helper.py
log_manager_cli/openfin_log_cli.py
log_manager_cli/version.py
oflog-0.3.0.dist-info/METADATA
oflog-0.3.0.dist-info/RECORD
oflog-0.3.0.dist-info/WHEEL
oflog-0.3.0.dist-info/entry_points.txt
oflog-0.3.0.dist-info/top_level.txt
