Metadata-Version: 2.1
Name: oflog
Version: 0.3.0
Summary: CLI for the OpenFin Log Management Service
Home-page: https://github.com/openfin/log-manager-cli
Author: OpenFin
Author-email: dev@openfin.co
License: UNKNOWN
Platform: UNKNOWN
Classifier: Programming Language :: Python :: 2.7
Classifier: License :: OSI Approved :: Apache Software License
Requires-Dist: requests (>=2.18.4)
Requires-Dist: pycrypto (>=2.6.1)
